metricsifter/__init__.py
metricsifter/sifter.py
metricsifter/utils.py
metricsifter/algo/__init__.py
metricsifter/algo/detection.py
metricsifter/algo/segmentation.py
metricsifter-0.0.1.dist-info/licenses/LICENSE
metricsifter-0.0.1.dist-info/METADATA
metricsifter-0.0.1.dist-info/WHEEL
metricsifter-0.0.1.dist-info/top_level.txt
metricsifter-0.0.1.dist-info/RECORD
