Metadata-Version: 2.4
Name: metricsifter
Version: 0.0.1
Summary: Feature Reduction for Multivariate Time Series Data
Author: yuuki
License-Expression: BSD-3-Clause
Project-URL: Homepage, https://github.com/ai4sre/metricsifter
Project-URL: Bug Tracker, https://github.com/ai4sre/metricsifter/issues
Classifier: Programming Language :: Python :: 3.10
Classifier: Programming Language :: Python :: 3.11
Classifier: Programming Language :: Python :: 3.12
Classifier: Programming Language :: Python :: 3.13
Classifier: Programming Language :: Python :: 3.14
Classifier: Operating System :: OS Independent
Requires-Python: >=3.10
License-File: LICENSE
Requires-Dist: numpy
Requires-Dist: pandas
Requires-Dist: scipy
Requires-Dist: joblib
Requires-Dist: ruptures
Requires-Dist: statsmodels
Requires-Dist: networkx
Provides-Extra: dev
Requires-Dist: black; extra == "dev"
Requires-Dist: ruff; extra == "dev"
Requires-Dist: coverage; extra == "dev"
Requires-Dist: pytest; extra == "dev"
Requires-Dist: setuptools; extra == "dev"
Provides-Extra: experiments
Requires-Dist: pandas-stubs; extra == "experiments"
Requires-Dist: scikit-learn<1.2,>=0.24; extra == "experiments"
Requires-Dist: hdbscan; extra == "experiments"
Requires-Dist: threadpoolctl; extra == "experiments"
Dynamic: license-file
